Workbook

Sheet Dashboard
A1: Personal Finance Manager
A2: Financial Dashboard
A4: Total Income | C4: =SUM(Transactions!G:G)
A5: Total Expenses | C5: =SUM(Transactions!H:H)
A6: Net Savings | C6: =B4-B5
A7: Monthly Budget | C7: 5000
A9: Expenses by Category | D9: Income vs Expenses
A14: Budget vs Actual
A15: Category | B15: Budget | C15: Actual | D15: Remaining | E15: % Used
A16: Housing | B16: 1200 | C16: =SUMIF(Categories!A:A,A16,Categories!B:B) | D16: =B16-C16 | E16: =IF(B16=0,0,C16/B16)
A17: Food | B17: 600 | C17: =SUMIF(Categories!A:A,A17,Categories!B:B) | D17: =B17-C17 | E17: =IF(B17=0,0,C17/B17)
A18: Transport | B18: 400 | C18: =SUMIF(Categories!A:A,A18,Categories!B:B) | D18: =B18-C18 | E18: =IF(B18=0,0,C18/B18)
A19: Entertainment | B19: 200 | C19: =SUMIF(Categories!A:A,A19,Categories!B:B) | D19: =B19-C19 | E19: =IF(B19=0,0,C19/B19)
A20: Utilities | B20: 300 | C20: =SUMIF(Categories!A:A,A20,Categories!B:B) | D20: =B20-C20 | E20: =IF(B20=0,0,C20/B20)
A21: Insurance | B21: 250 | C21: =SUMIF(Categories!A:A,A21,Categories!B:B) | D21: =B21-C21 | E21: =IF(B21=0,0,C21/B21)
A22: Savings | B22: 500 | C22: =SUMIF(Categories!A:A,A22,Categories!B:B) | D22: =B22-C22 | E22: =IF(B22=0,0,C22/B22)
A23: Other | B23: 200 | C23: =SUMIF(Categories!A:A,A23,Categories!B:B) | D23: =B23-C23 | E23: =IF(B23=0,0,C23/B23)

Sheet Transactions
A1: Income & Expense Log
A3: Date | B3: Description | C3: Category | D3: Type | E3: Payment Method | F3: Status | G3: Income | H3: Expense
A4: 1/1/2026 | B4: Salary - January | C4: Salary | D4: Income | E4: Bank Transfer | F4: Cleared | G4: 5000 | H4: 0
A5: 1/2/2026 | B5: Rent Payment | C5: Housing | D5: Expense | E5: Bank Transfer | F5: Cleared | G5: 0 | H5: 1200
A6: 1/3/2026 | B6: Groceries - Walmart | C6: Food | D6: Expense | E6: Credit Card | F6: Cleared | G6: 0 | H6: 350
A7: 1/5/2026 | B7: Gas Station | C7: Transport | D7: Expense | E7: Cash | F7: Pending | G7: 0 | H7: 80
A8: 1/7/2026 | B8: Netflix Subscription | C8: Entertainment | D8: Expense | E8: Credit Card | F8: Cleared | G8: 0 | H8: 15.99
A9: 1/10/2026 | B9: Freelance Project | C9: Freelance | D9: Income | E9: PayPal | F9: Cleared | G9: 1200 | H9: 0

Sheet Categories
A1: Category Master
A3: Category | B3: Budget | C3: Type
A4: Salary | B4: 5000 | C4: Income
A5: Freelance | B5: 2000 | C5: Income
A6: Investments | B6: 1000 | C6: Income
A7: Housing | B7: 1200 | C7: Expense
A8: Food | B8: 600 | C8: Expense
A9: Transport | B9: 400 | C9: Expense
A10: Entertainment | B10: 200 | C10: Expense
A11: Utilities | B11: 300 | C11: Expense
A12: Insurance | B12: 250 | C12: Expense
A13: Savings | B13: 500 | C13: Expense
A14: Healthcare | B14: 200 | C14: Expense
A15: Education | B15: 150 | C15: Expense
... A17: Other | B17: 200 | C17: Expense

Sheet Monthly Summary
A1: Monthly Reports
A3: Month | B3: Income | C3: Expenses | D3: Net | E3: Savings Rate
A4: January | B4: =SUMIFS(Transactions!G:G,Transactions!A:A,">="&DATE(2026,1,1),Transactions!A:A,"<="&DATE(2026,1,EOMONTH(DATE(2026,1,1),0))) | C4: =SUMIFS(Transactions!H:H,Transactions!A:A,">="&DATE(2026,1,1),Transactions!A:A,"<="&DATE(2026,1,EOMONTH(DATE(2026,1,1),0))) | D4: =B4-C4 | E4: =IF(B4=0,0,D4/B4)
A5: February | B5: =SUMIFS(Transactions!G:G,Transactions!A:A,">="&DATE(2026,2,1),Transactions!A:A,"<="&DATE(2026,2,EOMONTH(DATE(2026,2,1),0))) | C5: =SUMIFS(Transactions!H:H,Transactions!A:A,">="&DATE(2026,2,1),Transactions!A:A,"<="&DATE(2026,2,EOMONTH(DATE(2026,2,1),0))) | D5: =B5-C5 | E5: =IF(B5=0,0,D5/B5)
A6: March | B6: =SUMIFS(Transactions!G:G,Transactions!A:A,">="&DATE(2026,3,1),Transactions!A:A,"<="&DATE(2026,3,EOMONTH(DATE(2026,3,1),0))) | C6: =SUMIFS(Transactions!H:H,Transactions!A:A,">="&DATE(2026,3,1),Transactions!A:A,"<="&DATE(2026,3,EOMONTH(DATE(2026,3,1),0))) | D6: =B6-C6 | E6: =IF(B6=0,0,D6/B6)
A7: April | B7: =SUMIFS(Transactions!G:G,Transactions!A:A,">="&DATE(2026,4,1),Transactions!A:A,"<="&DATE(2026,4,EOMONTH(DATE(2026,4,1),0))) | C7: =SUMIFS(Transactions!H:H,Transactions!A:A,">="&DATE(2026,4,1),Transactions!A:A,"<="&DATE(2026,4,EOMONTH(DATE(2026,4,1),0))) | D7: =B7-C7 | E7: =IF(B7=0,0,D7/B7)
A8: May | B8: =SUMIFS(Transactions!G:G,Transactions!A:A,">="&DATE(2026,5,1),Transactions!A:A,"<="&DATE(2026,5,EOMONTH(DATE(2026,5,1),0))) | C8: =SUMIFS(Transactions!H:H,Transactions!A:A,">="&DATE(2026,5,1),Transactions!A:A,"<="&DATE(2026,5,EOMONTH(DATE(2026,5,1),0))) | D8: =B8-C8 | E8: =IF(B8=0,0,D8/B8)
A9: June | B9: =SUMIFS(Transactions!G:G,Transactions!A:A,">="&DATE(2026,6,1),Transactions!A:A,"<="&DATE(2026,6,EOMONTH(DATE(2026,6,1),0))) | C9: =SUMIFS(Transactions!H:H,Transactions!A:A,">="&DATE(2026,6,1),Transactions!A:A,"<="&DATE(2026,6,EOMONTH(DATE(2026,6,1),0))) | D9: =B9-C9 | E9: =IF(B9=0,0,D9/B9)
A10: July | B10: =SUMIFS(Transactions!G:G,Transactions!A:A,">="&DATE(2026,7,1),Transactions!A:A,"<="&DATE(2026,7,EOMONTH(DATE(2026,7,1),0))) | C10: =SUMIFS(Transactions!H:H,Transactions!A:A,">="&DATE(2026,7,1),Transactions!A:A,"<="&DATE(2026,7,EOMONTH(DATE(2026,7,1),0))) | D10: =B10-C10 | E10: =IF(B10=0,0,D10/B10)
A11: August | B11: =SUMIFS(Transactions!G:G,Transactions!A:A,">="&DATE(2026,8,1),Transactions!A:A,"<="&DATE(2026,8,EOMONTH(DATE(2026,8,1),0))) | C11: =SUMIFS(Transactions!H:H,Transactions!A:A,">="&DATE(2026,8,1),Transactions!A:A,"<="&DATE(2026,8,EOMONTH(DATE(2026,8,1),0))) | D11: =B11-C11 | E11: =IF(B11=0,0,D11/B11)
A12: September | B12: =SUMIFS(Transactions!G:G,Transactions!A:A,">="&DATE(2026,9,1),Transactions!A:A,"<="&DATE(2026,9,EOMONTH(DATE(2026,9,1),0))) | C12: =SUMIFS(Transactions!H:H,Transactions!A:A,">="&DATE(2026,9,1),Transactions!A:A,"<="&DATE(2026,9,EOMONTH(DATE(2026,9,1),0))) | D12: =B12-C12 | E12: =IF(B12=0,0,D12/B12)
A13: October | B13: =SUMIFS(Transactions!G:G,Transactions!A:A,">="&DATE(2026,10,1),Transactions!A:A,"<="&DATE(2026,10,EOMONTH(DATE(2026,10,1),0))) | C13: =SUMIFS(Transactions!H:H,Transactions!A:A,">="&DATE(2026,10,1),Transactions!A:A,"<="&DATE(2026,10,EOMONTH(DATE(2026,10,1),0))) | D13: =B13-C13 | E13: =IF(B13=0,0,D13/B13)
A14: November | B14: =SUMIFS(Transactions!G:G,Transactions!A:A,">="&DATE(2026,11,1),Transactions!A:A,"<="&DATE(2026,11,EOMONTH(DATE(2026,11,1),0))) | C14: =SUMIFS(Transactions!H:H,Transactions!A:A,">="&DATE(2026,11,1),Transactions!A:A,"<="&DATE(2026,11,EOMONTH(DATE(2026,11,1),0))) | D14: =B14-C14 | E14: =IF(B14=0,0,D14/B14)
A15: December | B15: =SUMIFS(Transactions!G:G,Transactions!A:A,">="&DATE(2026,12,1),Transactions!A:A,"<="&DATE(2026,12,EOMONTH(DATE(2026,12,1),0))) | C15: =SUMIFS(Transactions!H:H,Transactions!A:A,">="&DATE(2026,12,1),Transactions!A:A,"<="&DATE(2026,12,EOMONTH(DATE(2026,12,1),0))) | D15: =B15-C15 | E15: =IF(B15=0,0,D15/B15)

Sheet Savings Goals
A1: Savings Goals Tracker
A3: Goal | B3: Target | C3: Saved | D3: Remaining | E3: % Complete | F3: Deadline
A4: Emergency Fund | B4: 10000 | C4: 4500 | D4: =B4-C4 | E4: =IF(B4=0,0,C4/B4) | F4: Dec 2026
A5: New Car | B5: 25000 | C5: 5000 | D5: =B5-C5 | E5: =IF(B5=0,0,C5/B5) | F5: Jun 2027
A6: Vacation | B6: 5000 | C6: 2000 | D6: =B6-C6 | E6: =IF(B6=0,0,C6/B6) | F6: Aug 2026
A7: Education | B7: 15000 | C7: 3000 | D7: =B7-C7 | E7: =IF(B7=0,0,C7/B7) | F7: Jan 2028

Sheet How to Use
A1: How to Use This Template
A3: 📌 PERSONAL FINANCE MANAGER - USER GUIDE
A5: 1. TRANSACTIONS SHEET
A6: - Log all your income and expenses here
A7: - Select Type: Income or Expense
A8: - Income goes in column G, Expense in column H
A9: - Use the dropdown for transaction type
A11: 2. CATEGORIES SHEET
A12: - Edit/add your custom categories here
A13: - Set monthly budget for each expense category
A14: - Categories drive the reports and dashboard
A16: 3. DASHBOARD
... A39: Contact: acevedomoradavid433@gmail.com
